utility_metaclasses/__init__.py
utility_metaclasses/core/__init__.py
utility_metaclasses/core/immutable.py
utility_metaclasses/core/static.py
utility_metaclasses/py.typed
utility_metaclasses-0.1.1.dist-info/WHEEL
utility_metaclasses-0.1.1.dist-info/METADATA
utility_metaclasses-0.1.1.dist-info/RECORD
