Metadata-Version: 2.3
Name: utility-metaclasses
Version: 0.1.1
Summary: Collection of utility metaclasses
Author: NovaH00
Author-email: NovaH00 <trantay2006super@gmail.com>
Requires-Python: >=3.14
